lemonrunner/__init__.py
lemonrunner/lemonrunner.py
tests/__init__.py
tests/test_lemonrunner.py
lemonrunner-0.3.6.dist-info/LICENSE
lemonrunner-0.3.6.dist-info/METADATA
lemonrunner-0.3.6.dist-info/WHEEL
lemonrunner-0.3.6.dist-info/top_level.txt
lemonrunner-0.3.6.dist-info/RECORD
