Metadata-Version: 2.1
Name: lemonrunner
Version: 0.3.6
Home-page: https://github.com/sveinrou/lemonrunner
Author: sveinrou
Author-email: sveinrou@gmail.com
Classifier: Programming Language :: Python :: 3
Classifier: Operating System :: OS Independent
Requires-Python: >=3.6
License-File: LICENSE
